genyewatow/__init__.py
genyewatow/owo.py
genyewatow-1.0.0.dist-info/LICENSE
genyewatow-1.0.0.dist-info/METADATA
genyewatow-1.0.0.dist-info/WHEEL
genyewatow-1.0.0.dist-info/top_level.txt
genyewatow-1.0.0.dist-info/RECORD
