Metadata-Version: 2.1
Name: genyewatow
Version: 1.0.0
Summary: Awesome owo text genyewatow
Home-page: https://github.com/ombe1229/Genyewatow
Author: ombe1229
Author-email: h3236516@gmail.com
License: WTFPL License
Platform: UNKNOWN
License-File: LICENSE
